pylote/__init__.py
pylote/pylote.py
pylote-1.1.0.dist-info/LICENCE
pylote-1.1.0.dist-info/METADATA
pylote-1.1.0.dist-info/WHEEL
pylote-1.1.0.dist-info/top_level.txt
pylote-1.1.0.dist-info/RECORD
