Metadata-Version: 2.1
Name: pylote
Version: 1.1.0
Summary: Client Python pour interagir avec l'API Pilote (DITP).
Author-email: Colin Dugeai <colin.dugeai@modernisation.gouv.fr>
Project-URL: Homepage, https://github.com/DITP-pilotage/pylote
Project-URL: Issues, https://github.com/DITP-pilotage/pylote/issues
Requires-Python: >=3.8
License-File: LICENCE
Requires-Dist: requests
